{
    "info": {
        "_postman_id": "d2d7e197-2c71-4d14-96d8-2a6a106505bd",
        "name": "cashdrive-1.0",
        "schema": "https://schema.getpostman.com/json/collection/v2.0.0/collection.json"
    },
    "item": [{
        "name": "Authentication",
        "item": [{
            "name": "sign up",
            "_postman_id": "0ff26f7b-0f43-4230-bfaf-d1ac4bd32939",
            "request": {
                "method": "POST",
                "header": [{
                    "key": "Content-Type",
                    "value": "application/json",
                    "type": "text",
                    "disabled": true
                }, {
                    "key": "Accept",
                    "value": "application/json",
                    "type": "text"
                }],
                "body": {
                    "mode": "raw",
                    "raw": "{\r\n    'first_name':'test1',\r\n    'last_name':'test2',\r\n    'email':'forthes90@superrito.com',\r\n    'phone':'09012345678',\r\n    'password':'password',\r\n    'password_confirmation':'password',\r\n    'ref_code':'CD0003456'\r\n}",
                    "options": {
                        "raw": {
                            "language": "json"
                        }
                    }
                },
                "url": "http://localhost:8000/api/v1/signup"
            },
            "response": []
        }, {
            "name": "Login",
            "_postman_id": "7eb121df-b21a-4c27-a22f-0611b60dd1cb",
            "request": {
                "method": "POST",
                "header": [{
                    "warning": "This is a duplicate header and will be overridden by the Content-Type header generated by Postman.",
                    "key": "Content-Type",
                    "value": "application/json",
                    "type": "text"
                }],
                "body": {
                    "mode": "formdata",
                    "formdata": [{
                        "key": "email",
                        "value": "tosinezekiel20@gmail.com",
                        "type": "text"
                    }, {
                        "key": "password",
                        "value": "password",
                        "type": "text"
                    }],
                    "options": {
                        "raw": {
                            "language": "json"
                        }
                    }
                },
                "url": "http://localhost:8000/api/v1/signin"
            },
            "response": []
        }, {
            "name": "verify email callback",
            "_postman_id": "929af0f8-c414-46de-a3d5-2f625e61857d",
            "request": {
                "method": "POST",
                "header": [],
                "body": {
                    "mode": "raw",
                    "raw": "{\r\n    'token':'xGi6u2ZjVVDHPrvLHAa6CC58UYhVxmoq4NcGRtIhWFYSQk6MDuGCAOehjEBoLiTTiTHBiNaaRgqlzjLM'\r\n}",
                    "options": {
                        "raw": {
                            "language": "json"
                        }
                    }
                },
                "url": "http://localhost:8000/api/v1/verify-email"
            },
            "response": []
        }, {
            "name": "resend email verification link",
            "_postman_id": "d66e2da8-bb27-4d80-8116-13ee17dc3f4f",
            "request": {
                "method": "GET",
                "header": [],
                "url": "http://localhost:8000/api/v1/resend-email-verification/Serroustere1930@teleworm.us"
            },
            "response": []
        }, {
            "name": "password reset",
            "_postman_id": "edf666fe-b249-4eff-b104-1a5c743ca743",
            "request": {
                "method": "POST",
                "header": [],
                "body": {
                    "mode": "raw",
                    "raw": "{\r\n    'password':'123456',\r\n    'password_confirmation':'123456',\r\n    'email':'faight82@einrot.com'\r\n}",
                    "options": {
                        "raw": {
                            "language": "json"
                        }
                    }
                },
                "url": "http://localhost:8000/api/v1/reset-password"
            },
            "response": []
        }, {
            "name": "Verify Token",
            "_postman_id": "5abda61e-00c3-4a03-b003-6394e1ea6ede",
            "request": {
                "method": "GET",
                "header": [],
                "url": "http://localhost:8000/api/v1/verify-token/2T7jLmj9xokWBdlAsVYPsBjdvCmgKAncb7KqMwRhNoGckte3J0K1Pb2cdXULT5phKkZvvYBWsf8CYQjJ"
            },
            "response": []
        }, {
            "name": "get password reset link",
            "_postman_id": "e739f402-7e33-4527-a03f-4270f61a740f",
            "request": {
                "method": "POST",
                "header": [{
                    "key": "Accept",
                    "value": "application/json",
                    "type": "text"
                }, {
                    "key": "Content-Type",
                    "value": "application/json",
                    "type": "text"
                }],
                "body": {
                    "mode": "raw",
                    "raw": "{\r\n    'url':'reset-link',\r\n    'email':'faight82@einrot.com'\r\n}",
                    "options": {
                        "raw": {
                            "language": "json"
                        }
                    }
                },
                "url": "http://localhost:8000/api/v1/get-reset-link"
            },
            "response": []
        }, {
            "name": "verify email",
            "_postman_id": "3fbe93f8-52d4-4f55-972b-5be05710a7b2",
            "request": {
                "method": "GET",
                "header": [],
                "url": "http://localhost:8000/api/v1/verify-email/ZSkAVgwSXlW5QmWNSWTCWnAQWL484GkCL8TI4x7zbzuJ3GErOStIE2aA4rFWIN2kwiPcWEPLkmOn93t2"
            },
            "response": []
        }],
        "_postman_id": "a7646ffb-2af0-4348-9131-ac631101943a",
        "protocolProfileBehavior": {}
    }, {
        "name": "Loan",
        "item": [{
            "name": "Verify Plate Number",
            "_postman_id": "8ab7a219-7dad-4f6f-8f3a-00ee7bd13c0c",
            "request": {
                "method": "POST",
                "header": [{
                    "key": "Accept",
                    "value": "application/json",
                    "type": "text"
                }],
                "body": {
                    "mode": "raw",
                    "raw": "{\r\n    'platenumber':'EPE151FS',\r\n    'names':'ayotunde grace'\r\n}",
                    "options": {
                        "raw": {
                            "language": "json"
                        }
                    }
                },
                "url": "http://localhost:8000/api/v1/verify-plate-number"
            },
            "response": []
        }, {
            "name": "Estimate Loan",
            "_postman_id": "fac6c092-90e8-44a0-bb54-e060745d9667",
            "request": {
                "method": "POST",
                "header": [],
                "body": {
                    "mode": "raw",
                    "raw": "{\r\n    'desired_amount':800000,\r\n    'desired_tenor' : 6,\r\n    'desired_repayment_plan' : 1,\r\n    'year' : '2010',\r\n    'make' : 'Toyota',\r\n    'model' : 'Camry',\r\n    'trim' : 'LE V6',\r\n    'mileage' : '15000',\r\n    'insurance' : 'third party',\r\n    'registered_owner' : 1,\r\n    'state' : 'Lagos',\r\n    'plate_number' : 'lsd114dc'\r\n}",
                    "options": {
                        "raw": {
                            "language": "json"
                        }
                    }
                },
                "url": "http://localhost:8000/api/v1/estimate"
            },
            "response": []
        }, {
            "name": "Accept Loan",
            "_postman_id": "6ec2c5df-1495-42ec-9b92-8c4e728593c9",
            "request": {
                "auth": {
                    "type": "bearer",
                    "bearer": {
                        "token": "eyJ0eXAiOiJKV1QiLCJhbGciOiJIUzI1NiJ9.eyJpc3MiOiJodHRwOlwvXC9sb2NhbGhvc3Q6ODAwMFwvYXBpXC92MVwvc2lnbnVwIiwiaWF0IjoxNjAwMzQ2NTY3LCJleHAiOjE2MDAzNTAxNjcsIm5iZiI6MTYwMDM0NjU2NywianRpIjoiVjMycXZ5N3NJbzhaWGhmZiIsInN1YiI6MiwicHJ2IjoiODdlMGFmMWVmOWZkMTU4MTJmZGVjOTcxNTNhMTRlMGIwNDc1NDZhYSJ9.pZot4aPREg-dQECDCNtFeRNRUVxKEOmcxTM9BGqL52Q"
                    }
                },
                "method": "GET",
                "header": [],
                "url": "http://localhost:8000/api/v1/loans/1/accept"
            },
            "response": []
        }, {
            "name": "Decline Loan",
            "_postman_id": "bbd360b5-63d6-4cbb-b98b-241a7c28827b",
            "request": {
                "method": "GET",
                "header": [],
                "url": "http://localhost:8000/api/v1/loans/{loanapplication}/decline"
            },
            "response": []
        }, {
            "name": "Loan BreakDown",
            "_postman_id": "73a1e0bf-2deb-4023-a070-cbb0d5780358",
            "request": {
                "auth": {
                    "type": "bearer",
                    "bearer": {
                        "token": "eyJ0eXAiOiJKV1QiLCJhbGciOiJIUzI1NiJ9.eyJpc3MiOiJodHRwOlwvXC9sb2NhbGhvc3Q6ODAwMFwvYXBpXC92MVwvc2lnbmluIiwiaWF0IjoxNjAwMTgwNDQ1LCJleHAiOjE2MDAxODQwNDUsIm5iZiI6MTYwMDE4MDQ0NSwianRpIjoiUHRtOVhDZXBHeEJEYlE1MyIsInN1YiI6MSwicHJ2IjoiODdlMGFmMWVmOWZkMTU4MTJmZGVjOTcxNTNhMTRlMGIwNDc1NDZhYSJ9.YA0ZM7CEhDJnkcuou9wrr5bRc3Ecpym1rqdTkvJR4VI"
                    }
                },
                "method": "GET",
                "header": [],
                "url": "http://localhost:8000/api/v1/loans/1/breakdown"
            },
            "response": []
        }],
        "_postman_id": "08785a7d-26f1-45be-82df-2a5933197180",
        "protocolProfileBehavior": {}
    }, {
        "name": "KYC",
        "item": [{
            "name": "upload vehicle documents",
            "_postman_id": "8a6fd094-54bb-4ba6-ad2f-f24177b11dcf",
            "protocolProfileBehavior": {
                "disabledSystemHeaders": {
                    "content-type": true,
                    "accept": true
                }
            },
            "request": {
                "auth": {
                    "type": "bearer",
                    "bearer": {
                        "token": "eyJ0eXAiOiJKV1QiLCJhbGciOiJIUzI1NiJ9.eyJpc3MiOiJodHRwOlwvXC9sb2NhbGhvc3Q6ODAwMFwvYXBpXC92MVwvc2lnbmluIiwiaWF0IjoxNjAwMzQ4NzgxLCJleHAiOjE2MDAzNTIzODEsIm5iZiI6MTYwMDM0ODc4MSwianRpIjoiQUJlNm1ITzZTb0xOb08zZiIsInN1YiI6MiwicHJ2IjoiODdlMGFmMWVmOWZkMTU4MTJmZGVjOTcxNTNhMTRlMGIwNDc1NDZhYSJ9.E4ZhcudOZSBA8vRjAe0BA0Q6n6KV2VIK2aOkCVnIL40"
                    }
                },
                "method": "POST",
                "header": [{
                    "key": "Content-Type",
                    "value": "application/json",
                    "type": "text"
                }, {
                    "key": "Accept",
                    "value": "application/json",
                    "type": "text"
                }],
                "body": {
                    "mode": "formdata",
                    "formdata": [{
                        "key": "vehicle_id[]",
                        "value": "1",
                        "type": "text"
                    }, {
                        "key": "proof_of_ownership[]",
                        "type": "file",
                        "src": "/home/tunde/Pictures/ab1edb4394d067cfa540a672c5f6e4d9.jpg"
                    }, {
                        "key": "road_worthiness[]",
                        "type": "file",
                        "src": "/C:/Users/OluwatosinIkudayisi/Documents/Lightshot/cors.png"
                    }, {
                        "key": "license[]",
                        "type": "file",
                        "src": "/C:/Users/OluwatosinIkudayisi/Documents/Lightshot/chec.png"
                    }],
                    "options": {
                        "raw": {
                            "language": "json"
                        }
                    }
                },
                "url": "http://127.0.0.1:8000/api/v1/loans/1/vehicles/documents"
            },
            "response": []
        }, {
            "name": "Verify card charge",
            "_postman_id": "a7f7da0f-429b-4ff4-a7b0-f12bfa67b7c9",
            "request": {
                "auth": {
                    "type": "bearer",
                    "bearer": {
                        "token": "eyJ0eXAiOiJKV1QiLCJhbGciOiJIUzI1NiJ9.eyJpc3MiOiJodHRwOlwvXC9sb2NhbGhvc3Q6ODAwMFwvYXBpXC92MVwvc2lnbmluIiwiaWF0IjoxNjAxMTk5NjU2LCJleHAiOjE2MDEyMDMyNTYsIm5iZiI6MTYwMTE5OTY1NiwianRpIjoiYVFTRUE3bEdNdGJSb0NyUyIsInN1YiI6NCwicHJ2IjoiODdlMGFmMWVmOWZkMTU4MTJmZGVjOTcxNTNhMTRlMGIwNDc1NDZhYSJ9.GbdVngQckVoTby8AGuM9-lHUEHi6fHeE0oefvVV5KSk"
                    }
                },
                "method": "PUT",
                "header": [],
                "body": {
                    "mode": "raw",
                    "raw": "{\r\n    'reference':'x2lrl63ao0'\r\n}",
                    "options": {
                        "raw": {
                            "language": "json"
                        }
                    }
                },
                "url": "http://localhost:8000/api/v1/loans/3/card/payment/verify"
            },
            "response": []
        }, {
            "name": "Verify bank account details",
            "_postman_id": "e850791f-b05c-4a44-93c8-444dd89f928a",
            "request": {
                "auth": {
                    "type": "bearer",
                    "bearer": {
                        "token": "eyJ0eXAiOiJKV1QiLCJhbGciOiJIUzI1NiJ9.eyJpc3MiOiJodHRwOlwvXC9sb2NhbGhvc3Q6ODAwMFwvYXBpXC92MVwvc2lnbnVwIiwiaWF0IjoxNjAwMzQ2NTY3LCJleHAiOjE2MDAzNTAxNjcsIm5iZiI6MTYwMDM0NjU2NywianRpIjoiVjMycXZ5N3NJbzhaWGhmZiIsInN1YiI6MiwicHJ2IjoiODdlMGFmMWVmOWZkMTU4MTJmZGVjOTcxNTNhMTRlMGIwNDc1NDZhYSJ9.pZot4aPREg-dQECDCNtFeRNRUVxKEOmcxTM9BGqL52Q"
                    }
                },
                "method": "PUT",
                "header": [{
                    "key": "Content-Type",
                    "value": "application/json",
                    "type": "text"
                }, {
                    "key": "acc",
                    "value": "application/json",
                    "type": "text"
                }],
                "body": {
                    "mode": "raw",
                    "raw": "{\r\n    'name':'tosin ezekiel',\r\n    'number':'0763543863',\r\n    'type':'savings',\r\n    'bvn':'01234567890'\r\n}"
                },
                "url": "http://localhost:8000/api/v1/loans/1/banks/verify"
            },
            "response": []
        }, {
            "name": "Select Inspection Date",
            "_postman_id": "d0301fc8-f500-49a7-abd7-0d0f5eb64b42",
            "request": {
                "auth": {
                    "type": "bearer",
                    "bearer": {
                        "token": "eyJ0eXAiOiJKV1QiLCJhbGciOiJIUzI1NiJ9.eyJpc3MiOiJodHRwOlwvXC9sb2NhbGhvc3Q6ODAwMFwvYXBpXC92MVwvc2lnbmluIiwiaWF0IjoxNjAwMzQ4NzgxLCJleHAiOjE2MDAzNTIzODEsIm5iZiI6MTYwMDM0ODc4MSwianRpIjoiQUJlNm1ITzZTb0xOb08zZiIsInN1YiI6MiwicHJ2IjoiODdlMGFmMWVmOWZkMTU4MTJmZGVjOTcxNTNhMTRlMGIwNDc1NDZhYSJ9.E4ZhcudOZSBA8vRjAe0BA0Q6n6KV2VIK2aOkCVnIL40"
                    }
                },
                "method": "PUT",
                "header": [],
                "body": {
                    "mode": "raw",
                    "raw": "{\r\n\t'date':'2020-10-10',\r\n\t'time':'12:30 PM'\r\n}",
                    "options": {
                        "raw": {
                            "language": "json"
                        }
                    }
                },
                "url": "http://localhost:8000/api/v1/loans/1/vehicles/inspection"
            },
            "response": []
        }, {
            "name": "Select Card from List of Cards",
            "_postman_id": "2c32e6b3-5d15-4eb8-88c7-95d499cfe9d9",
            "request": {
                "auth": {
                    "type": "bearer",
                    "bearer": {
                        "token": "eyJ0eXAiOiJKV1QiLCJhbGciOiJIUzI1NiJ9.eyJpc3MiOiJodHRwOlwvXC9sb2NhbGhvc3Q6ODAwMFwvYXBpXC92MVwvc2lnbmluIiwiaWF0IjoxNTk4NTI2NTQzLCJleHAiOjE1OTg1MzAxNDMsIm5iZiI6MTU5ODUyNjU0MywianRpIjoiRzBZQXNodFRhbnhwQTFCcyIsInN1YiI6MSwicHJ2IjoiODdlMGFmMWVmOWZkMTU4MTJmZGVjOTcxNTNhMTRlMGIwNDc1NDZhYSJ9.uWfnofWLGHT0d2z0nMv9nte3NTqxHyTTim6KdaJls-U"
                    }
                },
                "method": "GET",
                "header": [],
                "url": "http://localhost:8000/api/v1/loans/1/card/{card}/select"
            },
            "response": []
        }, {
            "name": "Select Payment Type",
            "_postman_id": "f3db8e27-1091-4342-ab0e-7585a334300b",
            "request": {
                "method": "POST",
                "header": [],
                "body": {
                    "mode": "raw",
                    "raw": "{\r\n    'payment_type':'remita'\r\n}",
                    "options": {
                        "raw": {
                            "language": "json"
                        }
                    }
                },
                "url": "http://localhost:8000/api/v1/loans/1/payment-type/select"
            },
            "response": []
        }, {
            "name": "Get KYC Records",
            "_postman_id": "08a666ed-8a8b-497f-8618-4febe36e6013",
            "request": {
                "method": "POST",
                "header": [{
                    "key": "x-api-key",
                    "value": "F5vOSvxTeRujZdfyVB8kmyYunXt8LVh0aICr7cA9zJwZYsb4pPfbAFKzKDC2IanS",
                    "type": "text"
                }],
                "body": {
                    "mode": "raw",
                    "raw": "{'kyc_merchant_id':'639'}"
                },
                "url": "https://kycapis.creditclan.com/index.php/avs/request/records",
                "description": "Get KYC Records"
            },
            "response": []
        }, {
            "name": "https://kycapis.creditclan.com/index.php/avs/records",
            "_postman_id": "efeceb16-33fe-4718-b871-6535d9bee584",
            "request": {
                "method": "POST",
                "header": [{
                    "key": "x-api-key",
                    "value": "F5vOSvxTeRujZdfyVB8kmyYunXt8LVh0aICr7cA9zJwZYsb4pPfbAFKzKDC2IanS",
                    "type": "text"
                }],
                "body": {
                    "mode": "raw",
                    "raw": "{'kyc_merchant_id':'639'}",
                    "options": {
                        "raw": {
                            "language": "json"
                        }
                    }
                },
                "url": "https://kycapis.creditclan.com/index.php/avs/records"
            },
            "response": []
        }, {
            "name": "Get AVS Records",
            "_postman_id": "93f33b7e-0e4d-4f71-93ec-c0d482b95d72",
            "request": {
                "method": "POST",
                "header": [{
                    "key": "x-api-key",
                    "value": "F5vOSvxTeRujZdfyVB8kmyYunXt8LVh0aICr7cA9zJwZYsb4pPfbAFKzKDC2IanS",
                    "type": "text"
                }],
                "body": {
                    "mode": "raw",
                    "raw": "{'kyc_merchant_id':'639'}",
                    "options": {
                        "raw": {
                            "language": "json"
                        }
                    }
                },
                "url": "https://kycapis.creditclan.com/index.php/avs/records",
                "description": "Get AVS Records"
            },
            "response": []
        }],
        "_postman_id": "22175970-3143-4eb0-b8dd-a1f888d5de0c",
        "protocolProfileBehavior": {}
    }, {
        "name": "User",
        "item": [{
            "name": "My Info",
            "_postman_id": "a8593f77-c31e-4af0-9af4-5a1810c479ae",
            "request": {
                "auth": {
                    "type": "bearer",
                    "bearer": {
                        "token": "eyJ0eXAiOiJKV1QiLCJhbGciOiJIUzI1NiJ9.eyJpc3MiOiJodHRwOlwvXC9sb2NhbGhvc3Q6ODAwMFwvYXBpXC92MVwvc2lnbmluIiwiaWF0IjoxNjAwMTgwNDQ1LCJleHAiOjE2MDAxODQwNDUsIm5iZiI6MTYwMDE4MDQ0NSwianRpIjoiUHRtOVhDZXBHeEJEYlE1MyIsInN1YiI6MSwicHJ2IjoiODdlMGFmMWVmOWZkMTU4MTJmZGVjOTcxNTNhMTRlMGIwNDc1NDZhYSJ9.YA0ZM7CEhDJnkcuou9wrr5bRc3Ecpym1rqdTkvJR4VI"
                    }
                },
                "method": "GET",
                "header": [],
                "url": "http://localhost:8000/api/user"
            },
            "response": []
        }, {
            "name": "My Card List",
            "_postman_id": "cc94183a-90f6-4754-80e3-612bf6ba083f",
            "request": {
                "auth": {
                    "type": "bearer",
                    "bearer": {
                        "token": "eyJ0eXAiOiJKV1QiLCJhbGciOiJIUzI1NiJ9.eyJpc3MiOiJodHRwOlwvXC9sb2NhbGhvc3Q6ODAwMFwvYXBpXC92MVwvc2lnbmluIiwiaWF0IjoxNjAwMTgwNDQ1LCJleHAiOjE2MDAxODQwNDUsIm5iZiI6MTYwMDE4MDQ0NSwianRpIjoiUHRtOVhDZXBHeEJEYlE1MyIsInN1YiI6MSwicHJ2IjoiODdlMGFmMWVmOWZkMTU4MTJmZGVjOTcxNTNhMTRlMGIwNDc1NDZhYSJ9.YA0ZM7CEhDJnkcuou9wrr5bRc3Ecpym1rqdTkvJR4VI"
                    }
                },
                "method": "GET",
                "header": [],
                "url": "http://localhost:8000/api/v1/users/cards"
            },
            "response": []
        }, {
            "name": "Update My Profile",
            "_postman_id": "732887e3-a48b-4195-96f7-505962ec0ee8",
            "request": {
                "auth": {
                    "type": "bearer",
                    "bearer": {
                        "token": "eyJ0eXAiOiJKV1QiLCJhbGciOiJIUzI1NiJ9.eyJpc3MiOiJodHRwOlwvXC9sb2NhbGhvc3Q6ODAwMFwvYXBpXC92MVwvc2lnbmluIiwiaWF0IjoxNjAwMTgwNDQ1LCJleHAiOjE2MDAxODQwNDUsIm5iZiI6MTYwMDE4MDQ0NSwianRpIjoiUHRtOVhDZXBHeEJEYlE1MyIsInN1YiI6MSwicHJ2IjoiODdlMGFmMWVmOWZkMTU4MTJmZGVjOTcxNTNhMTRlMGIwNDc1NDZhYSJ9.YA0ZM7CEhDJnkcuou9wrr5bRc3Ecpym1rqdTkvJR4VI"
                    }
                },
                "method": "POST",
                "header": [],
                "body": {
                    "mode": "raw",
                    "raw": "{\r\n\t'first_name':'kehinde',\r\n\t'last_name':'akinleye',\r\n\t'phone':'09087896956'\r\n}",
                    "options": {
                        "raw": {
                            "language": "json"
                        }
                    }
                },
                "url": "http://localhost:8000/api/v1/users/update"
            },
            "response": []
        }, {
            "name": "My Loans",
            "_postman_id": "87c811e1-feda-4824-a2c2-8c438df21041",
            "request": {
                "auth": {
                    "type": "bearer",
                    "bearer": {
                        "token": "eyJ0eXAiOiJKV1QiLCJhbGciOiJIUzI1NiJ9.eyJpc3MiOiJodHRwOlwvXC9sb2NhbGhvc3Q6ODAwMFwvYXBpXC92MVwvc2lnbmluIiwiaWF0IjoxNjAwMTgwNDQ1LCJleHAiOjE2MDAxODQwNDUsIm5iZiI6MTYwMDE4MDQ0NSwianRpIjoiUHRtOVhDZXBHeEJEYlE1MyIsInN1YiI6MSwicHJ2IjoiODdlMGFmMWVmOWZkMTU4MTJmZGVjOTcxNTNhMTRlMGIwNDc1NDZhYSJ9.YA0ZM7CEhDJnkcuou9wrr5bRc3Ecpym1rqdTkvJR4VI"
                    }
                },
                "method": "GET",
                "header": [],
                "url": "http://localhost:8000/api/v1/users/loans"
            },
            "response": []
        }, {
            "name": "GetPayLink",
            "_postman_id": "e476aa8d-3cb1-434e-bdd5-29e033ae0aa7",
            "request": {
                "auth": {
                    "type": "bearer",
                    "bearer": {
                        "token": "eyJ0eXAiOiJKV1QiLCJhbGciOiJIUzI1NiJ9.eyJpc3MiOiJodHRwOlwvXC9sb2NhbGhvc3Q6ODAwMFwvYXBpXC92MVwvc2lnbmluIiwiaWF0IjoxNjAwNTQwMzU5LCJleHAiOjE2MDA1NDM5NTksIm5iZiI6MTYwMDU0MDM1OSwianRpIjoieHRvZDhRT1VReVFFQjhFTyIsInN1YiI6NiwicHJ2IjoiODdlMGFmMWVmOWZkMTU4MTJmZGVjOTcxNTNhMTRlMGIwNDc1NDZhYSJ9.D7YaTav_9T3dPrKJ_rMZTV-M2-f_XNLJTDgvCnc-og0"
                    }
                },
                "method": "GET",
                "header": [],
                "url": "127.0.0.1:8000/api/v1/get-pay-link"
            },
            "response": []
        }],
        "_postman_id": "0748f006-dac0-41b4-a242-ad63b6ca6634",
        "protocolProfileBehavior": {}
    }, {
        "name": "Admin",
        "item": [{
            "name": "Approve Loan",
            "_postman_id": "6fe7ae90-e9ee-4846-87f5-d6af7ca424b9",
            "request": {
                "auth": {
                    "type": "bearer",
                    "bearer": {
                        "token": "eyJ0eXAiOiJKV1QiLCJhbGciOiJIUzI1NiJ9.eyJpc3MiOiJodHRwOlwvXC9sb2NhbGhvc3Q6ODAwMFwvYXBpXC92MVwvc2lnbmluIiwiaWF0IjoxNjAwNTMyNzc5LCJleHAiOjE2MDA1MzYzNzksIm5iZiI6MTYwMDUzMjc3OSwianRpIjoiOE0wUWpKM0VjV2NMS09wOSIsInN1YiI6MSwicHJ2IjoiODdlMGFmMWVmOWZkMTU4MTJmZGVjOTcxNTNhMTRlMGIwNDc1NDZhYSJ9.tID99_G354h1cK9IYJWIPIiFEc-nxepT4ay_7bWDDfU"
                    }
                },
                "method": "PATCH",
                "header": [],
                "url": "http://localhost:8000/api/v1/loans/1/approve"
            },
            "response": []
        }, {
            "name": "Get All Users",
            "_postman_id": "b10a7f70-fdd1-46cb-8133-08d78cdbaeab",
            "request": {
                "auth": {
                    "type": "bearer",
                    "bearer": {
                        "token": "eyJ0eXAiOiJKV1QiLCJhbGciOiJIUzI1NiJ9.eyJpc3MiOiJodHRwOlwvXC9sb2NhbGhvc3Q6ODAwMFwvYXBpXC92MVwvc2lnbmluIiwiaWF0IjoxNjAwMzUxMDU5LCJleHAiOjE2MDAzNTQ2NTksIm5iZiI6MTYwMDM1MTA1OSwianRpIjoiWDZJRkYxMFFOaGd5SElCMSIsInN1YiI6MSwicHJ2IjoiODdlMGFmMWVmOWZkMTU4MTJmZGVjOTcxNTNhMTRlMGIwNDc1NDZhYSJ9.5FBPI8xE3NcyzuKKVmtZmdgtQbEbrf5osCFZpI-djRI"
                    }
                },
                "method": "GET",
                "header": [],
                "url": "http://localhost:8000/api/v1/users/all"
            },
            "response": []
        }, {
            "name": "Get Single User",
            "_postman_id": "5e7266a5-ebd8-4c3e-97f0-ae488e6e3a03",
            "request": {
                "auth": {
                    "type": "bearer",
                    "bearer": {
                        "token": "eyJ0eXAiOiJKV1QiLCJhbGciOiJIUzI1NiJ9.eyJpc3MiOiJodHRwOlwvXC9sb2NhbGhvc3Q6ODAwMFwvYXBpXC92MVwvc2lnbmluIiwiaWF0IjoxNjAwMTcxMDgyLCJleHAiOjE2MDAxNzQ2ODIsIm5iZiI6MTYwMDE3MTA4MiwianRpIjoid3Qxd0tuMDVtQ3RGek9zNyIsInN1YiI6MSwicHJ2IjoiODdlMGFmMWVmOWZkMTU4MTJmZGVjOTcxNTNhMTRlMGIwNDc1NDZhYSJ9.6bJDTCcbbrIqU9IeK0iSxamAA6umrJ8WylCOEctRXb0"
                    }
                },
                "method": "GET",
                "header": [],
                "url": "http://localhost:8000/api/v1/users/1"
            },
            "response": []
        }, {
            "name": "Get User Loans",
            "_postman_id": "17f72f43-14c0-483b-8f3b-f71c9893fa34",
            "request": {
                "auth": {
                    "type": "bearer",
                    "bearer": {
                        "token": "eyJ0eXAiOiJKV1QiLCJhbGciOiJIUzI1NiJ9.eyJpc3MiOiJodHRwOlwvXC9sb2NhbGhvc3Q6ODAwMFwvYXBpXC92MVwvc2lnbmluIiwiaWF0IjoxNjAwMTgwNDQ1LCJleHAiOjE2MDAxODQwNDUsIm5iZiI6MTYwMDE4MDQ0NSwianRpIjoiUHRtOVhDZXBHeEJEYlE1MyIsInN1YiI6MSwicHJ2IjoiODdlMGFmMWVmOWZkMTU4MTJmZGVjOTcxNTNhMTRlMGIwNDc1NDZhYSJ9.YA0ZM7CEhDJnkcuou9wrr5bRc3Ecpym1rqdTkvJR4VI"
                    }
                },
                "method": "GET",
                "header": [],
                "url": "http://localhost:8000/api/v1/users/2/loans"
            },
            "response": []
        }, {
            "name": "List All Loans",
            "_postman_id": "ad65a3f5-2c2e-4a61-9b61-e05000fc90f6",
            "request": {
                "auth": {
                    "type": "bearer",
                    "bearer": {
                        "token": "eyJ0eXAiOiJKV1QiLCJhbGciOiJIUzI1NiJ9.eyJpc3MiOiJodHRwOlwvXC9sb2NhbGhvc3Q6ODAwMFwvYXBpXC92MVwvc2lnbmluIiwiaWF0IjoxNjAwMTgwNDQ1LCJleHAiOjE2MDAxODQwNDUsIm5iZiI6MTYwMDE4MDQ0NSwianRpIjoiUHRtOVhDZXBHeEJEYlE1MyIsInN1YiI6MSwicHJ2IjoiODdlMGFmMWVmOWZkMTU4MTJmZGVjOTcxNTNhMTRlMGIwNDc1NDZhYSJ9.YA0ZM7CEhDJnkcuou9wrr5bRc3Ecpym1rqdTkvJR4VI"
                    }
                },
                "method": "GET",
                "header": [],
                "url": "http://localhost:8000/api/v1/loans"
            },
            "response": []
        }, {
            "name": "Get Verified Loans",
            "_postman_id": "f7c1efc3-f436-40a4-9d70-1d4e4ad94421",
            "request": {
                "auth": {
                    "type": "bearer",
                    "bearer": {
                        "token": "eyJ0eXAiOiJKV1QiLCJhbGciOiJIUzI1NiJ9.eyJpc3MiOiJodHRwOlwvXC9sb2NhbGhvc3Q6ODAwMFwvYXBpXC92MVwvc2lnbmluIiwiaWF0IjoxNjAwMTgwNDQ1LCJleHAiOjE2MDAxODQwNDUsIm5iZiI6MTYwMDE4MDQ0NSwianRpIjoiUHRtOVhDZXBHeEJEYlE1MyIsInN1YiI6MSwicHJ2IjoiODdlMGFmMWVmOWZkMTU4MTJmZGVjOTcxNTNhMTRlMGIwNDc1NDZhYSJ9.YA0ZM7CEhDJnkcuou9wrr5bRc3Ecpym1rqdTkvJR4VI"
                    }
                },
                "method": "GET",
                "header": [],
                "url": "http://localhost:8000/api/v1/loans/verified"
            },
            "response": []
        }, {
            "name": "Get single Loan",
            "_postman_id": "1596d394-9d19-41ee-b13c-8e35b36d91af",
            "request": {
                "auth": {
                    "type": "bearer",
                    "bearer": {
                        "token": "eyJ0eXAiOiJKV1QiLCJhbGciOiJIUzI1NiJ9.eyJpc3MiOiJodHRwOlwvXC9sb2NhbGhvc3Q6ODAwMFwvYXBpXC92MVwvc2lnbmluIiwiaWF0IjoxNjAwNTMyNzc5LCJleHAiOjE2MDA1MzYzNzksIm5iZiI6MTYwMDUzMjc3OSwianRpIjoiOE0wUWpKM0VjV2NMS09wOSIsInN1YiI6MSwicHJ2IjoiODdlMGFmMWVmOWZkMTU4MTJmZGVjOTcxNTNhMTRlMGIwNDc1NDZhYSJ9.tID99_G354h1cK9IYJWIPIiFEc-nxepT4ay_7bWDDfU"
                    }
                },
                "method": "GET",
                "header": [],
                "url": "http://localhost:8000/api/v1/loans/1"
            },
            "response": []
        }, {
            "name": "Reject Loan",
            "_postman_id": "c797017f-8bec-4030-bf76-041b70cc4693",
            "request": {
                "auth": {
                    "type": "bearer",
                    "bearer": {
                        "token": "eyJ0eXAiOiJKV1QiLCJhbGciOiJIUzI1NiJ9.eyJpc3MiOiJodHRwOlwvXC9sb2NhbGhvc3Q6ODAwMFwvYXBpXC92MVwvc2lnbmluIiwiaWF0IjoxNjAwMTgwNDQ1LCJleHAiOjE2MDAxODQwNDUsIm5iZiI6MTYwMDE4MDQ0NSwianRpIjoiUHRtOVhDZXBHeEJEYlE1MyIsInN1YiI6MSwicHJ2IjoiODdlMGFmMWVmOWZkMTU4MTJmZGVjOTcxNTNhMTRlMGIwNDc1NDZhYSJ9.YA0ZM7CEhDJnkcuou9wrr5bRc3Ecpym1rqdTkvJR4VI"
                    }
                },
                "method": "PATCH",
                "header": [],
                "url": "http://localhost:8000/api/v1/loans/1/reject"
            },
            "response": []
        }, {
            "name": "Give User Admin Role",
            "_postman_id": "0673f8be-357b-438b-a1a4-534c22ef8b20",
            "request": {
                "auth": {
                    "type": "bearer",
                    "bearer": {
                        "token": "eyJ0eXAiOiJKV1QiLCJhbGciOiJIUzI1NiJ9.eyJpc3MiOiJodHRwOlwvXC9sb2NhbGhvc3Q6ODAwMFwvYXBpXC92MVwvc2lnbmluIiwiaWF0IjoxNjAwMTgwNDQ1LCJleHAiOjE2MDAxODQwNDUsIm5iZiI6MTYwMDE4MDQ0NSwianRpIjoiUHRtOVhDZXBHeEJEYlE1MyIsInN1YiI6MSwicHJ2IjoiODdlMGFmMWVmOWZkMTU4MTJmZGVjOTcxNTNhMTRlMGIwNDc1NDZhYSJ9.YA0ZM7CEhDJnkcuou9wrr5bRc3Ecpym1rqdTkvJR4VI"
                    }
                },
                "method": "GET",
                "header": [],
                "url": "http://localhost:8000/api/v1/users/2/roles/admin/assign"
            },
            "response": []
        }, {
            "name": "Revoke User Admin Role",
            "_postman_id": "e40b735d-60d1-4ff7-a564-26619f229dcb",
            "request": {
                "auth": {
                    "type": "bearer",
                    "bearer": {
                        "token": "eyJ0eXAiOiJKV1QiLCJhbGciOiJIUzI1NiJ9.eyJpc3MiOiJodHRwOlwvXC9sb2NhbGhvc3Q6ODAwMFwvYXBpXC92MVwvc2lnbmluIiwiaWF0IjoxNjAwMTgwNDQ1LCJleHAiOjE2MDAxODQwNDUsIm5iZiI6MTYwMDE4MDQ0NSwianRpIjoiUHRtOVhDZXBHeEJEYlE1MyIsInN1YiI6MSwicHJ2IjoiODdlMGFmMWVmOWZkMTU4MTJmZGVjOTcxNTNhMTRlMGIwNDc1NDZhYSJ9.YA0ZM7CEhDJnkcuou9wrr5bRc3Ecpym1rqdTkvJR4VI"
                    }
                },
                "method": "GET",
                "header": [],
                "url": "http://localhost:8000/api/v1/users/2/roles/admin/revoke"
            },
            "response": []
        }, {
            "name": "Give Inspection Feedback",
            "_postman_id": "1c6bac51-850c-4aa3-ab0d-177cd3bc235a",
            "request": {
                "method": "PUT",
                "header": [],
                "body": {
                    "mode": "raw",
                    "raw": "{\r\n    'feedback':'Valid',\r\n    'status':true\r\n}",
                    "options": {
                        "raw": {
                            "language": "json"
                        }
                    }
                },
                "url": "http://localhost:8000/api/v1/loans/{loanapplication}/vehicles/feedback"
            },
            "response": []
        }],
        "_postman_id": "edcebc5a-7b09-4ca2-b6ac-b0b9cf0ee86c",
        "protocolProfileBehavior": {}
    }, {
        "name": "Payments",
        "item": [{
            "name": "Remita DD initiate",
            "_postman_id": "e8c7fa2b-6d02-41c2-b41f-133573317778",
            "request": {
                "auth": {
                    "type": "bearer",
                    "bearer": {
                        "token": "eyJ0eXAiOiJKV1QiLCJhbGciOiJIUzI1NiJ9.eyJpc3MiOiJodHRwOlwvXC9sb2NhbGhvc3Q6ODAwMFwvYXBpXC92MVwvc2lnbmluIiwiaWF0IjoxNjAyMDc0MDk2LCJleHAiOjE2MDIwNzc2OTYsIm5iZiI6MTYwMjA3NDA5NiwianRpIjoib3hDaDhpbXNKSWh5cHRZNCIsInN1YiI6MiwicHJ2IjoiODdlMGFmMWVmOWZkMTU4MTJmZGVjOTcxNTNhMTRlMGIwNDc1NDZhYSJ9.IeAXf_Ct7extdU2HZstQr_c5JULbvVJagcR7dwT6vsc"
                    }
                },
                "method": "POST",
                "header": [],
                "body": {
                    "mode": "raw",
                    "raw": "{\r\n\t'payer_account': '1234890001',\r\n\t'payer_bank_code': '057',\r\n\t'payer_email': 'segunakomolafe5@gmail.com',\r\n\t'payer_name': 'ADEYEMI JAMES',\r\n\t'payer_phone': '2345089765645'\r\n} ",
                    "options": {
                        "raw": {
                            "language": "json"
                        }
                    }
                },
                "url": "http://localhost:8000/api/v1/loans/1/direct-debit/initiate"
            },
            "response": []
        }, {
            "name": "Validate OTP",
            "_postman_id": "448214e2-e5fe-41bf-9b7e-7e63d639d2ce",
            "request": {
                "auth": {
                    "type": "bearer",
                    "bearer": {
                        "token": "eyJ0eXAiOiJKV1QiLCJhbGciOiJIUzI1NiJ9.eyJpc3MiOiJodHRwOlwvXC9sb2NhbGhvc3Q6ODAwMFwvYXBpXC92MVwvc2lnbmluIiwiaWF0IjoxNjAyMDYwMTk3LCJleHAiOjE2MDIwNjM3OTcsIm5iZiI6MTYwMjA2MDE5NywianRpIjoiaUM2aEFIdWU0T1FMQ01QdiIsInN1YiI6MiwicHJ2IjoiODdlMGFmMWVmOWZkMTU4MTJmZGVjOTcxNTNhMTRlMGIwNDc1NDZhYSJ9.K-Jwhp1fHIsBwavVaOjkSXPxV2eI_3yX2xM6NMMIAL8"
                    }
                },
                "method": "POST",
                "header": [],
                "body": {
                    "mode": "raw",
                    "raw": "{\r\n    'card':'0441234567890',\r\n    'otp':'1234'\r\n}",
                    "options": {
                        "raw": {
                            "language": "json"
                        }
                    }
                },
                "url": "http://localhost:8000/api/v1/loans/payment/remita/1/validate-otp"
            },
            "response": []
        }, {
            "name": "Request OTP",
            "_postman_id": "c5069ac9-5226-4a3b-b4ac-c8ecbab5ade0",
            "request": {
                "auth": {
                    "type": "bearer",
                    "bearer": {
                        "token": "eyJ0eXAiOiJKV1QiLCJhbGciOiJIUzI1NiJ9.eyJpc3MiOiJodHRwOlwvXC9sb2NhbGhvc3Q6ODAwMFwvYXBpXC92MVwvc2lnbmluIiwiaWF0IjoxNjAyMDYwMTk3LCJleHAiOjE2MDIwNjM3OTcsIm5iZiI6MTYwMjA2MDE5NywianRpIjoiaUM2aEFIdWU0T1FMQ01QdiIsInN1YiI6MiwicHJ2IjoiODdlMGFmMWVmOWZkMTU4MTJmZGVjOTcxNTNhMTRlMGIwNDc1NDZhYSJ9.K-Jwhp1fHIsBwavVaOjkSXPxV2eI_3yX2xM6NMMIAL8"
                    }
                },
                "method": "GET",
                "header": [],
                "url": "http://localhost:8000/api/v1/loans/payment/remita/1/request-otp"
            },
            "response": []
        }, {
            "name": "Send Debit Instruction",
            "_postman_id": "61ab4d70-6082-4775-895a-819dd30b7f83",
            "request": {
                "method": "POST",
                "header": [],
                "url": "http://localhost:8000/api/v1/loans/payment/remita/1/validate-otp"
            },
            "response": []
        }, {
            "name": "Mandate Status",
            "_postman_id": "a9980956-ff35-41ff-a3b6-53e02f0e3fd3",
            "request": {
                "auth": {
                    "type": "bearer",
                    "bearer": {
                        "token": "eyJ0eXAiOiJKV1QiLCJhbGciOiJIUzI1NiJ9.eyJpc3MiOiJodHRwOlwvXC9sb2NhbGhvc3Q6ODAwMFwvYXBpXC92MVwvc2lnbmluIiwiaWF0IjoxNjAyMDc0MDk2LCJleHAiOjE2MDIwNzc2OTYsIm5iZiI6MTYwMjA3NDA5NiwianRpIjoib3hDaDhpbXNKSWh5cHRZNCIsInN1YiI6MiwicHJ2IjoiODdlMGFmMWVmOWZkMTU4MTJmZGVjOTcxNTNhMTRlMGIwNDc1NDZhYSJ9.IeAXf_Ct7extdU2HZstQr_c5JULbvVJagcR7dwT6vsc"
                    }
                },
                "method": "GET",
                "header": [],
                "url": "http://localhost:8000/api/v1/remita/1/status"
            },
            "response": []
        }, {
            "name": "Mandate History",
            "_postman_id": "4e15ba5a-9159-491e-bafe-f837335e9c3c",
            "request": {
                "auth": {
                    "type": "bearer",
                    "bearer": {
                        "token": "eyJ0eXAiOiJKV1QiLCJhbGciOiJIUzI1NiJ9.eyJpc3MiOiJodHRwOlwvXC9sb2NhbGhvc3Q6ODAwMFwvYXBpXC92MVwvc2lnbmluIiwiaWF0IjoxNjAyMDc0MDk2LCJleHAiOjE2MDIwNzc2OTYsIm5iZiI6MTYwMjA3NDA5NiwianRpIjoib3hDaDhpbXNKSWh5cHRZNCIsInN1YiI6MiwicHJ2IjoiODdlMGFmMWVmOWZkMTU4MTJmZGVjOTcxNTNhMTRlMGIwNDc1NDZhYSJ9.IeAXf_Ct7extdU2HZstQr_c5JULbvVJagcR7dwT6vsc"
                    }
                },
                "method": "GET",
                "header": [],
                "url": "http://localhost:8000/api/v1/remita/1/history"
            },
            "response": []
        }, {
            "name": "Cancel Mandate",
            "_postman_id": "3f11dc9f-74c3-4b93-8c37-9f5468e2e7eb",
            "request": {
                "auth": {
                    "type": "bearer",
                    "bearer": {
                        "token": "eyJ0eXAiOiJKV1QiLCJhbGciOiJIUzI1NiJ9.eyJpc3MiOiJodHRwOlwvXC9sb2NhbGhvc3Q6ODAwMFwvYXBpXC92MVwvc2lnbmluIiwiaWF0IjoxNjAyMDc0MDk2LCJleHAiOjE2MDIwNzc2OTYsIm5iZiI6MTYwMjA3NDA5NiwianRpIjoib3hDaDhpbXNKSWh5cHRZNCIsInN1YiI6MiwicHJ2IjoiODdlMGFmMWVmOWZkMTU4MTJmZGVjOTcxNTNhMTRlMGIwNDc1NDZhYSJ9.IeAXf_Ct7extdU2HZstQr_c5JULbvVJagcR7dwT6vsc"
                    }
                },
                "method": "GET",
                "header": [],
                "url": "http://localhost:8000/api/v1/remita/1/cancel"
            },
            "response": []
        }, {
            "name": "Stop mandate",
            "_postman_id": "720094f2-ae0d-405f-b7cc-13c77bc085d1",
            "request": {
                "auth": {
                    "type": "bearer",
                    "bearer": {
                        "token": "eyJ0eXAiOiJKV1QiLCJhbGciOiJIUzI1NiJ9.eyJpc3MiOiJodHRwOlwvXC9sb2NhbGhvc3Q6ODAwMFwvYXBpXC92MVwvc2lnbmluIiwiaWF0IjoxNjAyMDc0MDk2LCJleHAiOjE2MDIwNzc2OTYsIm5iZiI6MTYwMjA3NDA5NiwianRpIjoib3hDaDhpbXNKSWh5cHRZNCIsInN1YiI6MiwicHJ2IjoiODdlMGFmMWVmOWZkMTU4MTJmZGVjOTcxNTNhMTRlMGIwNDc1NDZhYSJ9.IeAXf_Ct7extdU2HZstQr_c5JULbvVJagcR7dwT6vsc"
                    }
                },
                "method": "GET",
                "header": [],
                "url": "http://localhost:8000/api/v1/remita/1/stop"
            },
            "response": []
        }],
        "_postman_id": "077f428e-d9c3-489c-8632-d63340b02679",
        "protocolProfileBehavior": {}
    }, {
        "name": "Open",
        "item": [{
            "name": "Car Value",
            "_postman_id": "056429e2-856d-40b0-9421-51b2917921c4",
            "request": {
                "method": "POST",
                "header": [],
                "body": {
                    "mode": "raw",
                    "raw": "{\r\n    'year':'2017',\r\n    'make':'Toyota',\r\n    'model':'Camry'\r\n}",
                    "options": {
                        "raw": {
                            "language": "json"
                        }
                    }
                },
                "url": "http://localhost:8000/api/v1/car-value"
            },
            "response": []
        }, {
            "name": "How much can i borrow",
            "_postman_id": "c69d56e8-5480-4c9d-889d-5df1849ead44",
            "request": {
                "method": "POST",
                "header": [],
                "body": {
                    "mode": "raw",
                    "raw": "{\r\n    'year':'2017',\r\n    'make':'Toyota',\r\n    'model':'Camry',\r\n    'trim':'LE 4dr Sedan (2.5L 4cyl 6A)'\r\n}",
                    "options": {
                        "raw": {
                            "language": "json"
                        }
                    }
                },
                "url": "http://localhost:8000/api/v1/how-much-can-i-borrow"
            },
            "response": []
        }],
        "_postman_id": "957b875d-bc2b-40d3-8c5a-ef068b1cf021",
        "protocolProfileBehavior": {}
    }],
    "protocolProfileBehavior": {}
}